baya/__init__.py
baya/_version.py
baya/backend.py
baya/context_processors.py
baya/dynamic_roles.py
baya/membership.py
baya/mock_ldap_helpers.py
baya/permissions.py
baya/utils.py
baya/visitors.py
baya/admin/__init__.py
baya/admin/options.py
baya/admin/sites.py
baya/templatetags/__init__.py
baya/templatetags/baya_tags.py
baya/tests/__init__.py
baya/tests/admin.py
baya/tests/directory.py
baya/tests/manage.py
baya/tests/models.py
baya/tests/nested_urls1.py
baya/tests/nested_urls2.py
baya/tests/settings.py
baya/tests/test_admin.py
baya/tests/test_backend.py
baya/tests/test_base.py
baya/tests/test_dynamic_roles.py
baya/tests/test_integration.py
baya/tests/test_mock_ldap_helpers.py
baya/tests/test_nodes.py
baya/tests/test_permissions.py
baya/tests/test_templatetags.py
baya/tests/test_visitors.py
baya/tests/urls.py
baya/tests/views.py
baya/tests/submod/__init__.py
baya/tests/submod/models.py
baya/tests/submod2/__init__.py
baya/tests/submod2/admin.py
baya/tests/submod2/models.py
baya/tests/submod2/urls.py
testsite/__init__.py
testsite/manage.py
testsite/settings.py
testsite/urls.py
testsite/wsgi.py
testsite/baya/__init__.py
testsite/baya/_version.py
testsite/baya/backend.py
testsite/baya/context_processors.py
testsite/baya/dynamic_roles.py
testsite/baya/membership.py
testsite/baya/mock_ldap_helpers.py
testsite/baya/permissions.py
testsite/baya/utils.py
testsite/baya/visitors.py
testsite/baya/admin/__init__.py
testsite/baya/admin/options.py
testsite/baya/admin/sites.py
testsite/baya/templatetags/__init__.py
testsite/baya/templatetags/baya_tags.py
testsite/baya/tests/__init__.py
testsite/baya/tests/admin.py
testsite/baya/tests/directory.py
testsite/baya/tests/manage.py
testsite/baya/tests/models.py
testsite/baya/tests/nested_urls1.py
testsite/baya/tests/nested_urls2.py
testsite/baya/tests/settings.py
testsite/baya/tests/test_admin.py
testsite/baya/tests/test_backend.py
testsite/baya/tests/test_base.py
testsite/baya/tests/test_dynamic_roles.py
baya-2.0.2.dist-info/LICENSE
baya-2.0.2.dist-info/METADATA
baya-2.0.2.dist-info/WHEEL
baya-2.0.2.dist-info/top_level.txt
baya-2.0.2.dist-info/RECORD
