Metadata-Version: 2.1
Name: baya
Version: 2.0.2
Summary: Nested LDAP Groups authorization.
Home-page: https://github.com/counsyl/baya
Author: Steven Buss
Author-email: steven.buss@gmail.com
Maintainer: Counsyl Platform Team
Maintainer-email: platform@counsyl.com
License: MIT
Download-URL: https://github.com/counsyl/baya/tarball/v2.0.2
Platform: UNKNOWN
Classifier: Development Status :: 3 - Alpha
Classifier: Intended Audience :: Developers
Classifier: Operating System :: OS Independent
Classifier: Programming Language :: Python
Classifier: Programming Language :: Python :: 2
Classifier: Programming Language :: Python :: 2.7
Classifier: Programming Language :: Python :: 3
Classifier: Programming Language :: Python :: 3.5
Requires-Dist: django-auth-ldap (>=1.2.8)
Requires-Dist: Django (<2.2,>=1.11)
Requires-Dist: six (>=1.3)
Provides-Extra: development
Requires-Dist: mockldap (>=0.2.0) ; extra == 'development'
